{
    "title": "The Other Hobbs Family Cookbook",
    "titleURL": "extras/Title.md",
    "headerColor": "lightgray",
    "titleColor": "lightblue",
    "categories": [
        {
            "title": "Recipes",
            "files": [
                "recipes/ButterDips.md",
                "recipes/CaribbeanCorn.md",
                "recipes/GroundBeefChili.md",
                "recipes/Margarita.md",
                "recipes/PancakesWaffles.md",
                "recipes/PizzaCrust.md",
                "recipes/PizzaSauce.md"
            ]
        },
        {
            "title": "Extras",
            "files": [
                "extras/Links.md",
                "extras/Conversions.md"
            ]
        }
    ]
}
